Metadata-Version: 2.1
Name: cgmhc
Version: 0.1.1
Summary: Tools for finding MHC alleles for WGS/RNAseq samples
Home-page: http://github.com/compgen-io/cgmhc/
Author: Marcus Breese
Author-email: marcus@breese.com
License: UNKNOWN
Platform: UNKNOWN
Requires-Python: >=3.9
License-File: LICENSE
